insardev_toolkit/ASF.py
insardev_toolkit/EOF.py
insardev_toolkit/HTTP.py
insardev_toolkit/MultiInstanceManager.py
insardev_toolkit/NCubeVTK.py
insardev_toolkit/Tiles.py
insardev_toolkit/XYZTiles.py
insardev_toolkit/__init__.py
insardev_toolkit/datagrid.py
insardev_toolkit/progressbar.py
insardev_toolkit/progressbar_joblib.py
insardev_toolkit-2025.5.6.dev0.dist-info/licenses/LICENSE
insardev_toolkit-2025.5.6.dev0.dist-info/METADATA
insardev_toolkit-2025.5.6.dev0.dist-info/WHEEL
insardev_toolkit-2025.5.6.dev0.dist-info/top_level.txt
insardev_toolkit-2025.5.6.dev0.dist-info/RECORD
